examples/__init__.py
examples/cool_api.py
examples/gdbm_example.py
yaci/__init__.py
yaci/base_storage.py
yaci/cache_manager.py
yaci/contexts.py
yaci/dict_storage.py
yaci-0.5.2.dist-info/LICENSE.txt
yaci-0.5.2.dist-info/METADATA
yaci-0.5.2.dist-info/WHEEL
yaci-0.5.2.dist-info/top_level.txt
yaci-0.5.2.dist-info/RECORD
