Metadata-Version: 2.1
Name: yaci
Version: 0.5.2
Summary: Yet Another Cache Implementation
Home-page: UNKNOWN
Author: Aquil H. Abdullah
Author-email: aquil.abdullah@gmail.com
License: UNKNOWN
Platform: UNKNOWN
Classifier: Programming Language :: Python :: 2.7
Classifier: Programming Language :: Python :: 3
Classifier: Programming Language :: Python :: 3.4
Classifier: Programming Language :: Python :: 3.5
Classifier: Programming Language :: Python :: 3.6
Classifier: Programming Language :: Python :: 3.7
Requires-Dist: six
